spark_rapids_ml/__init__.py
spark_rapids_ml/__main__.py
spark_rapids_ml/classification.py
spark_rapids_ml/clustering.py
spark_rapids_ml/connect_plugin.py
spark_rapids_ml/core.py
spark_rapids_ml/feature.py
spark_rapids_ml/install.py
spark_rapids_ml/knn.py
spark_rapids_ml/numpy_allocator.py
spark_rapids_ml/params.py
spark_rapids_ml/pipeline.py
spark_rapids_ml/pyspark_rapids.py
spark_rapids_ml/regression.py
spark_rapids_ml/spark_rapids_submit.py
spark_rapids_ml/tree.py
spark_rapids_ml/tuning.py
spark_rapids_ml/umap.py
spark_rapids_ml/utils.py
spark_rapids_ml/common/__init__.py
spark_rapids_ml/common/cuml_context.py
spark_rapids_ml/jars/com.nvidia.rapids.ml-25.12.0.jar
spark_rapids_ml/metrics/MulticlassMetrics.py
spark_rapids_ml/metrics/RegressionMetrics.py
spark_rapids_ml/metrics/__init__.py
spark_rapids_ml/metrics/utils.py
spark_rapids_ml-25.12.0.dist-info/METADATA
spark_rapids_ml-25.12.0.dist-info/WHEEL
spark_rapids_ml-25.12.0.dist-info/entry_points.txt
spark_rapids_ml-25.12.0.dist-info/top_level.txt
spark_rapids_ml-25.12.0.dist-info/RECORD
