Metadata-Version: 2.4
Name: spark-rapids-ml
Version: 25.12.0
Summary: Apache Spark integration with RAPIDS and cuML
Author-email: Jinfeng Li <jinfeng@nvidia.com>, Bobby Wang <bobwang@nvidia.com>, Erik Ordentlich <eordentlich@nvidia.com>, Lee Yang <leey@nvidia.com>
Classifier: Programming Language :: Python :: 3
Classifier: Programming Language :: Python :: 3.10
Classifier: Programming Language :: Python :: 3.11
Classifier: License :: OSI Approved :: Apache Software License
Classifier: Operating System :: OS Independent
Classifier: Environment :: GPU :: NVIDIA CUDA :: 12
Classifier: Environment :: GPU :: NVIDIA CUDA :: 12 :: 12.0
Classifier: Environment :: GPU :: NVIDIA CUDA :: 12 :: 12.1
Classifier: Environment :: GPU :: NVIDIA CUDA :: 12 :: 12.2
Classifier: Environment :: GPU :: NVIDIA CUDA :: 12 :: 12.3
Classifier: Environment :: GPU :: NVIDIA CUDA :: 12 :: 12.4
Classifier: Environment :: GPU :: NVIDIA CUDA :: 12 :: 12.5
Requires-Python: >=3.10
